setup.py
src/exceptional/__init__.py
src/pylons_exceptional.egg-info/PKG-INFO
src/pylons_exceptional.egg-info/SOURCES.txt
src/pylons_exceptional.egg-info/dependency_links.txt
src/pylons_exceptional.egg-info/top_level.txt