Metadata-Version: 1.0
Name: pylons-exceptional
Version: 0.2.3
Summary: A pylons client for Exceptional (getexceptional.com), ported from django-exceptional
Home-page: http://github.com/DataDog/pylons-exceptional
Author: Alexis Le-Quoc
Author-email: alq@datadoghq.com
License: UNKNOWN
Platform: UNKNOWN
